README.md
setup.py
aimage/__init__.py
aimage/aimage.py
aimage/eater_renderer.py
aimage/head.py
aimage/img.py
aimage/stub_data_loader.py
aimage/stub_data_loader_od.py
aimage/ui.py
aimage.egg-info/PKG-INFO
aimage.egg-info/SOURCES.txt
aimage.egg-info/dependency_links.txt
aimage.egg-info/not-zip-safe
aimage.egg-info/requires.txt
aimage.egg-info/top_level.txt
aimage/eater/application/image2image_server.py
aimage/eater/application/image2json_server.py
aimage/eater/bridge/__init__.py
aimage/eater/bridge/client.py
aimage/eater/bridge/protocol.py
aimage/eater/bridge/server.py
test/test_rectangle.py