Metadata-Version: 2.1
Name: aimage
Version: 1.3.5
Summary: Native aimage library wrapper for internal use.
Home-page: https://github.com/aieater/python_async_image_library
Author: Pegara, Inc.
Author-email: support@pegara.com
License: MIT
Keywords: async video image computer vision deeplearning machinelarning augmentation
Platform: UNKNOWN
Classifier: License :: OSI Approved :: MIT License
Classifier: Operating System :: OS Independent
Classifier: Programming Language :: Python :: 3
Classifier: Programming Language :: Python :: 3.5
Classifier: Programming Language :: Python :: 3.6
Classifier: Programming Language :: Python :: 3.7
Classifier: Programming Language :: Python :: 3.8
